pyDNase/__init__.py
pyDNase/_version.py
pyDNase/data/IMR90_6mer.pickle
pyDNase/data/example.bam
pyDNase/data/example.bam.bai
pyDNase/data/example.bed
pyDNase/footprinting/WellingtonC.cpython-36m-darwin.so
pyDNase/footprinting/__init__.py
pyDNase-0.2.6.data/scripts/dnase_average_profile.py
pyDNase-0.2.6.data/scripts/dnase_bias_estimator.py
pyDNase-0.2.6.data/scripts/dnase_cut_counter.py
pyDNase-0.2.6.data/scripts/dnase_ddhs_scorer.py
pyDNase-0.2.6.data/scripts/dnase_to_JSON.py
pyDNase-0.2.6.data/scripts/dnase_to_javatreeview.py
pyDNase-0.2.6.data/scripts/dnase_wig_tracks.py
pyDNase-0.2.6.data/scripts/example_footprint_scores.py
pyDNase-0.2.6.data/scripts/wellington_bootstrap.py
pyDNase-0.2.6.data/scripts/wellington_footprints.py
pyDNase-0.2.6.dist-info/DESCRIPTION.rst
pyDNase-0.2.6.dist-info/METADATA
pyDNase-0.2.6.dist-info/RECORD
pyDNase-0.2.6.dist-info/WHEEL
pyDNase-0.2.6.dist-info/metadata.json
pyDNase-0.2.6.dist-info/top_level.txt
