Metadata-Version: 2.0
Name: pyDNase
Version: 0.2.6
Summary: DNase-seq analysis library
Home-page: http://jpiper.github.io/pyDNase
Author: Jason Piper
Author-email: j.piper@me.com
License: MIT
Platform: UNKNOWN
Requires-Dist: numpy
Requires-Dist: matplotlib (<2.0.0)
Requires-Dist: pysam (>=0.8.1)
Requires-Dist: clint (>=0.3.2)
